flake8_cls_attr_order/__init__.py
flake8_cls_attr_order/meta.py
flake8_cls_attr_order/plugin.py
flake8_cls_attr_order-0.3.0.dist-info/LICENSE.md
flake8_cls_attr_order-0.3.0.dist-info/METADATA
flake8_cls_attr_order-0.3.0.dist-info/WHEEL
flake8_cls_attr_order-0.3.0.dist-info/entry_points.txt
flake8_cls_attr_order-0.3.0.dist-info/top_level.txt
flake8_cls_attr_order-0.3.0.dist-info/RECORD
