Metadata-Version: 2.1
Name: flake8-cls-attr-order
Version: 0.3.0
Summary: Flake8 plugin to check class attributes order
Home-page: https://github.com/vyahello/flake8-cls-attr-order
Author: Vladimir Yahello
Author-email: vyahello@gmail.com
License: UNKNOWN
Platform: UNKNOWN
Classifier: Framework :: Flake8
Classifier: Environment :: Console
Classifier: Intended Audience :: Developers
Classifier: License :: OSI Approved :: MIT License
Classifier: Programming Language :: Python
Classifier: Programming Language :: Python :: 3.7
Classifier: Programming Language :: Python :: 3.8
Classifier: Programming Language :: Python :: 3.9
Classifier: Programming Language :: Python :: 3.10
Classifier: Topic :: Software Development :: Libraries :: Python Modules
Classifier: Topic :: Software Development :: Quality Assurance
License-File: LICENSE.md
Requires-Dist: flake8 (==4.0.1)
Requires-Dist: astpretty (==2.1.0)
